natural/__init__.py
natural/bank.py
natural/constant.py
natural/data.py
natural/date.py
natural/file.py
natural/language.py
natural/number.py
natural/phone.py
natural/size.py
natural/text.py
natural/util.py
natural/locale/af_ZA/LC_MESSAGES/natural.mo
natural/locale/de_DE/LC_MESSAGES/natural.mo
natural/locale/en_GB/LC_MESSAGES/natural.mo
natural/locale/en_US/LC_MESSAGES/natural.mo
natural/locale/es_ES/LC_MESSAGES/natural.mo
natural/locale/fr_FR/LC_MESSAGES/natural.mo
natural/locale/ja_JP/LC_MESSAGES/natural.mo
natural/locale/nl_NL/LC_MESSAGES/natural.mo
natural-0.1.7.dist-info/DESCRIPTION.rst
natural-0.1.7.dist-info/METADATA
natural-0.1.7.dist-info/RECORD
natural-0.1.7.dist-info/WHEEL
natural-0.1.7.dist-info/metadata.json
natural-0.1.7.dist-info/top_level.txt
