Metadata-Version: 2.0
Name: natural
Version: 0.1.7
Summary: Convert data to their natural (human-readable) format
Home-page: https://github.com/tehmaze/natural
Author: Wijnand Modderman-Lenstra
Author-email: maze@pyth0n.org
License: MIT
Keywords: natural data date file number size
Platform: UNKNOWN
Requires-Dist: six
